fastmcp_agents/library/agent/elasticsearch/__init__.py
fastmcp_agents/library/agent/elasticsearch/elasticsearch.py.disabled
fastmcp_agents/library/agent/elasticsearch/esql_agent.py
fastmcp_agents/library/agent/elasticsearch/esql_expert.py
fastmcp_agents/library/agent/elasticsearch/shared.py
fastmcp_agents_library_agent_elasticsearch-0.5.7.dist-info/WHEEL
fastmcp_agents_library_agent_elasticsearch-0.5.7.dist-info/entry_points.txt
fastmcp_agents_library_agent_elasticsearch-0.5.7.dist-info/METADATA
fastmcp_agents_library_agent_elasticsearch-0.5.7.dist-info/RECORD
