Metadata-Version: 2.3
Name: fastmcp-agents-library-agent-elasticsearch
Version: 0.5.7
Summary: An agent for interacting with Elasticsearch
Requires-Dist: fastmcp-agents-library-mcp
Requires-Dist: fastmcp-ai-agent-bridge-pydantic-ai>=0.1.0
Requires-Dist: gitpython>=3.1.44
Requires-Dist: pydantic>=2.11.7
Requires-Python: >=3.13
